cieloApi3/__init__.py
cieloApi3/address.py
cieloApi3/cieloEcommerce.py
cieloApi3/creditCard.py
cieloApi3/customer.py
cieloApi3/environment.py
cieloApi3/merchant.py
cieloApi3/objectJSON.py
cieloApi3/payment.py
cieloApi3/recurrentPayment.py
cieloApi3/sale.py
cieloApi3/settings.py
cieloApi3/request/__init__.py
cieloApi3/request/base.py
cieloApi3/request/createCardToken.py
cieloApi3/request/createSale.py
cieloApi3/request/deactivateRecorrency.py
cieloApi3/request/queryRecorrency.py
cieloApi3/request/querySale.py
cieloApi3/request/reactivateRecorrency.py
cieloApi3/request/updateSale.py
cieloApi3_b2bit-2021.8.19.dist-info/LICENSE
cieloApi3_b2bit-2021.8.19.dist-info/METADATA
cieloApi3_b2bit-2021.8.19.dist-info/WHEEL
cieloApi3_b2bit-2021.8.19.dist-info/top_level.txt
cieloApi3_b2bit-2021.8.19.dist-info/RECORD
