Metadata-Version: 2.1
Name: cieloApi3-b2bit
Version: 2021.8.19
Summary: SDK API-3.0 Python Cielo
Home-page: https://github.com/math-s/API-3.0-Python
Author: Matheus Andrade
Author-email: matheus.andrade1996@gmail.com
License: MIT
Keywords: api3.0 cielo python sdk ecommerce
Platform: UNKNOWN
Classifier: Intended Audience :: Developers
Classifier: Natural Language :: English
Classifier: License :: OSI Approved :: MIT License
Classifier: Programming Language :: Python
Classifier: Programming Language :: Python :: 2.6
Classifier: Programming Language :: Python :: 2.7
Classifier: Programming Language :: Python :: 3.4
Classifier: Programming Language :: Python :: 3.5
License-File: LICENSE
Requires-Dist: requests
Requires-Dist: future
